alu.v
`timescale 1ns / 1ps

module alu #(
    parameter WIDTH = 8
)(
    input  wire [WIDTH-1:0] a,
    input  wire [WIDTH-1:0] b,
    input  wire [3:0] opcode,
    input  wire enable,

    output reg  [WIDTH-1:0] result,
    output wire zero,
    output wire carry,
    output wire overflow
);

    // Internal signals
    reg [WIDTH:0] temp;   // Extra bit for carry

    // ==========================================================
    // Opcode Mapping:
    // 0000 - ADD
    // 0001 - SUB
    // 0010 - AND
    // 0011 - OR
    // 0100 - XOR
    // 0101 - NOT (A)
    // 0110 - SHIFT LEFT
    // 0111 - SHIFT RIGHT
    // 1000 - INCREMENT
    // 1001 - DECREMENT
    // 1010 - COMPARE
    // ==========================================================

    always @(*) begin
        if (enable) begin
            case (opcode)

                4'b0000: temp = a + b;          // ADD
                4'b0001: temp = a - b;          // SUB
                4'b0010: temp = a & b;          // AND
                4'b0011: temp = a | b;          // OR
                4'b0100: temp = a ^ b;          // XOR
                4'b0101: temp = ~a;             // NOT
                4'b0110: temp = a << 1;         // SHIFT LEFT
                4'b0111: temp = a >> 1;         // SHIFT RIGHT
                4'b1000: temp = a + 1;          // INCREMENT
                4'b1001: temp = a - 1;          // DECREMENT
                4'b1010: temp = (a == b) ? 1 : 0; // COMPARE

                // Safe default to avoid undefined behavior
                default: temp = 0;

            endcase
        end else begin
            // Low-power: operand isolation
            temp = 0;
        end

        result = temp[WIDTH-1:0];
    end

    // ===========================
    // FLAG GENERATION
    // ===========================

    assign zero     = (result == 0);
    assign carry    = temp[WIDTH];
    assign overflow = (opcode == 4'b0000) ? ((a[WIDTH-1] == b[WIDTH-1]) && (result[WIDTH-1] != a[WIDTH-1])) :
                      (opcode == 4'b0001) ? ((a[WIDTH-1] != b[WIDTH-1]) && (result[WIDTH-1] != a[WIDTH-1])) :
                      1'b0;

endmodule

tb_alu.v
`timescale 1ns / 1ps

module alu_tb;

    parameter WIDTH = 8;

    reg [WIDTH-1:0] a, b;
    reg [3:0] opcode;
    reg enable;

    wire [WIDTH-1:0] result;
    wire zero, carry, overflow;

    // Instantiate ALU
    alu #(WIDTH) uut (
        .a(a),
        .b(b),
        .opcode(opcode),
        .enable(enable),
        .result(result),
        .zero(zero),
        .carry(carry),
        .overflow(overflow)
    );

    initial begin

        $dumpfile("alu.vcd");
        $dumpvars(0, alu_tb);

        $display("Starting ALU Test...");

        enable = 1;

        // ===============================
        // Test All Operations
        // ===============================

        a = 10; b = 5;

        opcode = 0; #10; // ADD
        opcode = 1; #10; // SUB
        opcode = 2; #10; // AND
        opcode = 3; #10; // OR
        opcode = 4; #10; // XOR
        opcode = 5; #10; // NOT
        opcode = 6; #10; // SHL
        opcode = 7; #10; // SHR
        opcode = 8; #10; // INC
        opcode = 9; #10; // DEC
        opcode = 10; #10; // COMPARE

        // ===============================
        // Edge Cases
        // ===============================

        a = 255; b = 1; opcode = 0; #10; // Overflow case
        a = 0; b = 0; opcode = 0; #10;   // Zero flag

        // ===============================
        // Invalid Opcode Check
        // ===============================

        opcode = 15; #10;
        if (opcode > 10)
            $display("Warning: Invalid opcode at time %0t", $time);

        // ===============================
        // Low Power Check
        // ===============================

        enable = 0; opcode = 0; #10;

        $display("Test Completed.");
        $finish;

    end

endmodule

alu.vcd
$date
	Sun Jun 21 18:44:08 2026
$end
$version
	Icarus Verilog
$end
$timescale
	1ps
$end
$scope module alu_tb $end
$var wire 1 ! zero $end
$var wire 8 " result [7:0] $end
$var wire 1 # overflow $end
$var wire 1 $ carry $end
$var parameter 32 % WIDTH $end
$var reg 8 & a [7:0] $end
$var reg 8 ' b [7:0] $end
$var reg 1 ( enable $end
$var reg 4 ) opcode [3:0] $end
$scope module uut $end
$var wire 8 * a [7:0] $end
$var wire 8 + b [7:0] $end
$var wire 1 ( enable $end
$var wire 4 , opcode [3:0] $end
$var wire 1 ! zero $end
$var wire 1 # overflow $end
$var wire 1 $ carry $end
$var parameter 32 - WIDTH $end
$var reg 8 . result [7:0] $end
$var reg 9 / temp [8:0] $end
$upscope $end
$upscope $end
$enddefinitions $end
$comment Show the parameter values. $end
$dumpall
b1000 -
b1000 %
$end
#0
$dumpvars
b1111 /
b1111 .
b0 ,
b101 +
b1010 *
b0 )
1(
b101 '
b1010 &
0$
0#
b1111 "
0!
$end
#10000
b101 "
b101 .
b101 /
b1 )
b1 ,
#20000
1!
b0 "
b0 .
b0 /
b10 )
b10 ,
#30000
0!
b1111 "
b1111 .
b1111 /
b11 )
b11 ,
#40000
b100 )
b100 ,
#50000
1$
b11110101 "
b11110101 .
b111110101 /
b101 )
b101 ,
#60000
0$
b10100 "
b10100 .
b10100 /
b110 )
b110 ,
#70000
b101 "
b101 .
b101 /
b111 )
b111 ,
#80000
b1011 "
b1011 .
b1011 /
b1000 )
b1000 ,
#90000
b1001 "
b1001 .
b1001 /
b1001 )
b1001 ,
#100000
1!
b0 "
b0 .
b0 /
b1010 )
b1010 ,
#110000
1$
b100000000 /
b0 )
b0 ,
b1 '
b1 +
b11111111 &
b11111111 *
#120000
0$
b0 /
b0 '
b0 +
b0 &
b0 *
#130000
b1111 )
b1111 ,
#140000
b0 )
b0 ,
0(
